mcp_jsondiff_kel/__init__.py
mcp_jsondiff_kel/__main__.py
mcp_jsondiff_kel/server.py
mcp_jsondiff-0.1.0.dist-info/METADATA
mcp_jsondiff-0.1.0.dist-info/WHEEL
mcp_jsondiff-0.1.0.dist-info/top_level.txt
mcp_jsondiff-0.1.0.dist-info/RECORD
